materials_informatics_agent-0.1.24.dist-info/licenses/LICENSE.txt
mi_agent/__init__.py
mi_agent/__main__.py
mi_agent/app_config.py
mi_agent/config.py
mi_agent/extractors.py
mi_agent/orchestrator.py
mi_agent/states.py
mi_agent/utils.py
mi_agent/nodes/baseline.py
mi_agent/nodes/data_explainer.py
mi_agent/nodes/eda_executor.py
mi_agent/nodes/eda_plan.py
mi_agent/nodes/feature_selection.py
mi_agent/nodes/file_paths.py
mi_agent/nodes/merge.py
mi_agent/nodes/model_explanation.py
mi_agent/nodes/report.py
mi_agent/nodes/tuning.py
materials_informatics_agent-0.1.24.dist-info/METADATA
materials_informatics_agent-0.1.24.dist-info/WHEEL
materials_informatics_agent-0.1.24.dist-info/entry_points.txt
materials_informatics_agent-0.1.24.dist-info/top_level.txt
materials_informatics_agent-0.1.24.dist-info/RECORD
