Metadata-Version: 2.4
Name: materials_informatics_agent
Version: 0.1.24
Summary: A LangGraph/LLM‐driven EDA → AutoML → report pipeline
Home-page: https://github.com/hasan-sayeed/MI-Agent
Author: Hasan Sayeed
Author-email: hasan.sayeed.71.93@gmail.com
License: MIT
Project-URL: Source, https://github.com/hasan-sayeed/MI-Agent
Classifier: Programming Language :: Python :: 3.10
Classifier: License :: OSI Approved :: MIT License
Classifier: Operating System :: OS Independent
Requires-Python: >=3.10
License-File: LICENSE.txt
Requires-Dist: pandas==2.1.4
Requires-Dist: numpy==1.26.4
Requires-Dist: langchain-core==0.3.51
Requires-Dist: langchain-openai==0.3.12
Requires-Dist: langchain-experimental==0.3.4
Requires-Dist: trustcall==0.0.38
Requires-Dist: pydantic==2.11.3
Requires-Dist: langgraph==0.3.26
Requires-Dist: langsmith==0.3.27
Requires-Dist: pycaret==3.3.2
Requires-Dist: optuna==4.3.0
Requires-Dist: optuna-integration==4.3.0
Requires-Dist: markdown==3.8
Requires-Dist: pdfkit==1.0.0
Requires-Dist: matplotlib==3.7.5
Requires-Dist: seaborn==0.13.2
Requires-Dist: python-dotenv==1.1.0
Provides-Extra: pdf
Requires-Dist: weasyprint>=57.0; extra == "pdf"
Dynamic: author
Dynamic: classifier
Dynamic: description
Dynamic: description-content-type
Dynamic: home-page
Dynamic: license-file
Dynamic: requires-dist
Dynamic: requires-python
Dynamic: summary
